labadmin/__init__.py
labadmin/admin.py
labadmin/apps.py
labadmin/forms.py
labadmin/models.py
labadmin/notifications.py
labadmin/permissions.py
labadmin/serializers.py
labadmin/settings.py
labadmin/tests.py
labadmin/urls.py
labadmin/views.py
labadmin/locale/en/LC_MESSAGES/django.mo
labadmin/locale/en/LC_MESSAGES/django.po
labadmin/locale/it/LC_MESSAGES/django.mo
labadmin/locale/it/LC_MESSAGES/django.po
labadmin/migrations/0001_initial.py
labadmin/migrations/0002_auto_20160927_1249.py
labadmin/migrations/0003_card_credits.py
labadmin/migrations/0004_logcredits.py
labadmin/migrations/0005_auto_20161012_1223.py
labadmin/migrations/0006_device_token.py
labadmin/migrations/0007_remove_role_role_kind.py
labadmin/migrations/0008_logaccess_device.py
labadmin/migrations/0009_logerror_device.py
labadmin/migrations/0010_remove_logaccess_users.py
labadmin/migrations/0011_sketch.py
labadmin/migrations/0012_auto_20170518_2158.py
labadmin/migrations/0013_auto_20170520_1959.py
labadmin/migrations/__init__.py
labadmin/templates/labadmin/base.html
labadmin/templates/labadmin/index.html
labadmin/templates/labadmin/login.html
labadmin/templates/labadmin/password_change_done.html
labadmin/templates/labadmin/password_change_form.html
labadmin/templates/labadmin/password_reset_complete.html
labadmin/templates/labadmin/password_reset_confirm.html
labadmin/templates/labadmin/password_reset_done.html
labadmin/templates/labadmin/password_reset_email.html
labadmin/templates/labadmin/password_reset_form.html
labadmin/templates/labadmin/userprofile.html
labadmin/templates/registration/activate.html
labadmin/templates/registration/activation_complete.html
labadmin/templates/registration/activation_email.txt
labadmin/templates/registration/activation_email_subject.txt
labadmin/templates/registration/registration_complete.html
labadmin/templates/registration/registration_form.html
labadmin/utils/__init__.py
labadmin/utils/fablabto/README.md
labadmin/utils/fablabto/__init__.py
labadmin-0.5.1.dist-info/LICENSE.md
labadmin-0.5.1.dist-info/METADATA
labadmin-0.5.1.dist-info/WHEEL
labadmin-0.5.1.dist-info/top_level.txt
labadmin-0.5.1.dist-info/RECORD
