Metadata-Version: 2.1
Name: labadmin
Version: 0.5.1
Summary: A django app to manage your Fablab
Home-page: https://github.com/OfficineArduinoTorino/labadmin.git
Author: Officine Torino
Author-email: d.gomba@officine.cc
License: MIT
Keywords: Fablab,lab,admin
Platform: UNKNOWN
Classifier: Development Status :: 3 - Alpha
Classifier: Framework :: Django
Classifier: Framework :: Django :: 1.8
Classifier: Framework :: Django :: 1.10
Classifier: Framework :: Django :: 1.11
Classifier: Intended Audience :: Developers
Classifier: Natural Language :: English
Classifier: Programming Language :: Python :: 3.4
Classifier: Programming Language :: Python :: 3.5
Classifier: Programming Language :: Python :: 3.6
Requires-Dist: django (<1.11,>=1.8)
Requires-Dist: djangorestframework (<3.7,>3)
Requires-Dist: django-cors-middleware (==1.3.1)
Requires-Dist: django-oauth-toolkit (==0.10.0)
Requires-Dist: django-registration (<2.3,>=2.2)
Requires-Dist: django-versatileimagefield (<2,>=1.7.0)
Requires-Dist: paho-mqtt (<2,>1)
Requires-Dist: Pillow (<4.1)
